{"nodes": [{"id": "home_sasi_desktop_dev_rm_orbit_rmbook_src_hooks_usewebrtc_js", "label": "useWebRTC.js", "file_type": "code", "source_file": "/home/sasi/Desktop/dev/RM Orbit/RMBook/src/hooks/useWebRTC.js", "source_location": "L1"}, {"id": "usewebrtc_usewebrtc", "label": "useWebRTC()", "file_type": "code", "source_file": "/home/sasi/Desktop/dev/RM Orbit/RMBook/src/hooks/useWebRTC.js", "source_location": "L28"}], "edges": [{"source": "home_sasi_desktop_dev_rm_orbit_rmbook_src_hooks_usewebrtc_js", "target": "react", "relation": "imports_from", "confidence": "EXTRACTED", "source_file": "/home/sasi/Desktop/dev/RM Orbit/RMBook/src/hooks/useWebRTC.js", "source_location": "L16", "weight": 1.0}, {"source": "home_sasi_desktop_dev_rm_orbit_rmbook_src_hooks_usewebrtc_js", "target": "socket_io_client", "relation": "imports_from", "confidence": "EXTRACTED", "source_file": "/home/sasi/Desktop/dev/RM Orbit/RMBook/src/hooks/useWebRTC.js", "source_location": "L17", "weight": 1.0}, {"source": "home_sasi_desktop_dev_rm_orbit_rmbook_src_hooks_usewebrtc_js", "target": "usewebrtc_usewebrtc", "relation": "contains", "confidence": "EXTRACTED", "source_file": "/home/sasi/Desktop/dev/RM Orbit/RMBook/src/hooks/useWebRTC.js", "source_location": "L28", "weight": 1.0}], "raw_calls": [{"caller_nid": "usewebrtc_usewebrtc", "callee": "useState", "source_file": "/home/sasi/Desktop/dev/RM Orbit/RMBook/src/hooks/useWebRTC.js", "source_location": "L29"}, {"caller_nid": "usewebrtc_usewebrtc", "callee": "useState", "source_file": "/home/sasi/Desktop/dev/RM Orbit/RMBook/src/hooks/useWebRTC.js", "source_location": "L30"}, {"caller_nid": "usewebrtc_usewebrtc", "callee": "useState", "source_file": "/home/sasi/Desktop/dev/RM Orbit/RMBook/src/hooks/useWebRTC.js", "source_location": "L31"}, {"caller_nid": "usewebrtc_usewebrtc", "callee": "useState", "source_file": "/home/sasi/Desktop/dev/RM Orbit/RMBook/src/hooks/useWebRTC.js", "source_location": "L32"}, {"caller_nid": "usewebrtc_usewebrtc", "callee": "useState", "source_file": "/home/sasi/Desktop/dev/RM Orbit/RMBook/src/hooks/useWebRTC.js", "source_location": "L33"}, {"caller_nid": "usewebrtc_usewebrtc", "callee": "useState", "source_file": "/home/sasi/Desktop/dev/RM Orbit/RMBook/src/hooks/useWebRTC.js", "source_location": "L34"}, {"caller_nid": "usewebrtc_usewebrtc", "callee": "useRef", "source_file": "/home/sasi/Desktop/dev/RM Orbit/RMBook/src/hooks/useWebRTC.js", "source_location": "L36"}, {"caller_nid": "usewebrtc_usewebrtc", "callee": "useRef", "source_file": "/home/sasi/Desktop/dev/RM Orbit/RMBook/src/hooks/useWebRTC.js", "source_location": "L37"}, {"caller_nid": "usewebrtc_usewebrtc", "callee": "useRef", "source_file": "/home/sasi/Desktop/dev/RM Orbit/RMBook/src/hooks/useWebRTC.js", "source_location": "L38"}, {"caller_nid": "usewebrtc_usewebrtc", "callee": "useRef", "source_file": "/home/sasi/Desktop/dev/RM Orbit/RMBook/src/hooks/useWebRTC.js", "source_location": "L39"}, {"caller_nid": "usewebrtc_usewebrtc", "callee": "useRef", "source_file": "/home/sasi/Desktop/dev/RM Orbit/RMBook/src/hooks/useWebRTC.js", "source_location": "L40"}, {"caller_nid": "usewebrtc_usewebrtc", "callee": "useRef", "source_file": "/home/sasi/Desktop/dev/RM Orbit/RMBook/src/hooks/useWebRTC.js", "source_location": "L41"}, {"caller_nid": "usewebrtc_usewebrtc", "callee": "useEffect", "source_file": "/home/sasi/Desktop/dev/RM Orbit/RMBook/src/hooks/useWebRTC.js", "source_location": "L111"}, {"caller_nid": "usewebrtc_usewebrtc", "callee": "useCallback", "source_file": "/home/sasi/Desktop/dev/RM Orbit/RMBook/src/hooks/useWebRTC.js", "source_location": "L268"}, {"caller_nid": "usewebrtc_usewebrtc", "callee": "useCallback", "source_file": "/home/sasi/Desktop/dev/RM Orbit/RMBook/src/hooks/useWebRTC.js", "source_location": "L275"}, {"caller_nid": "usewebrtc_usewebrtc", "callee": "useCallback", "source_file": "/home/sasi/Desktop/dev/RM Orbit/RMBook/src/hooks/useWebRTC.js", "source_location": "L282"}]}