{"nodes": [{"id": "home_sasi_desktop_dev_rm_orbit_card_src_pages_cardeditor_tsx", "label": "CardEditor.tsx", "file_type": "code", "source_file": "/home/sasi/Desktop/dev/RM Orbit/Card/src/pages/CardEditor.tsx", "source_location": "L1"}, {"id": "cardeditor_set", "label": "set()", "file_type": "code", "source_file": "/home/sasi/Desktop/dev/RM Orbit/Card/src/pages/CardEditor.tsx", "source_location": "L135"}, {"id": "cardeditor_addlink", "label": "addLink()", "file_type": "code", "source_file": "/home/sasi/Desktop/dev/RM Orbit/Card/src/pages/CardEditor.tsx", "source_location": "L138"}, {"id": "cardeditor_updatelink", "label": "updateLink()", "file_type": "code", "source_file": "/home/sasi/Desktop/dev/RM Orbit/Card/src/pages/CardEditor.tsx", "source_location": "L141"}, {"id": "cardeditor_removelink", "label": "removeLink()", "file_type": "code", "source_file": "/home/sasi/Desktop/dev/RM Orbit/Card/src/pages/CardEditor.tsx", "source_location": "L148"}, {"id": "cardeditor_handlesave", "label": "handleSave()", "file_type": "code", "source_file": "/home/sasi/Desktop/dev/RM Orbit/Card/src/pages/CardEditor.tsx", "source_location": "L151"}, {"id": "cardeditor_copysecret", "label": "copySecret()", "file_type": "code", "source_file": "/home/sasi/Desktop/dev/RM Orbit/Card/src/pages/CardEditor.tsx", "source_location": "L180"}, {"id": "cardeditor_isedit", "label": "isEdit()", "file_type": "code", "source_file": "/home/sasi/Desktop/dev/RM Orbit/Card/src/pages/CardEditor.tsx", "source_location": "L408"}], "edges": [{"source": "home_sasi_desktop_dev_rm_orbit_card_src_pages_cardeditor_tsx", "target": "react", "relation": "imports_from", "confidence": "EXTRACTED", "source_file": "/home/sasi/Desktop/dev/RM Orbit/Card/src/pages/CardEditor.tsx", "source_location": "L1", "weight": 1.0}, {"source": "home_sasi_desktop_dev_rm_orbit_card_src_pages_cardeditor_tsx", "target": "react_router_dom", "relation": "imports_from", "confidence": "EXTRACTED", "source_file": "/home/sasi/Desktop/dev/RM Orbit/Card/src/pages/CardEditor.tsx", "source_location": "L2", "weight": 1.0}, {"source": "home_sasi_desktop_dev_rm_orbit_card_src_pages_cardeditor_tsx", "target": "lucide_react", "relation": "imports_from", "confidence": "EXTRACTED", "source_file": "/home/sasi/Desktop/dev/RM Orbit/Card/src/pages/CardEditor.tsx", "source_location": "L3", "weight": 1.0}, {"source": "home_sasi_desktop_dev_rm_orbit_card_src_pages_cardeditor_tsx", "target": "home_sasi_desktop_dev_rm_orbit_card_src_services_api", "relation": "imports_from", "confidence": "EXTRACTED", "source_file": "/home/sasi/Desktop/dev/RM Orbit/Card/src/pages/CardEditor.tsx", "source_location": "L7", "weight": 1.0}, {"source": "home_sasi_desktop_dev_rm_orbit_card_src_pages_cardeditor_tsx", "target": "home_sasi_desktop_dev_rm_orbit_card_src_types", "relation": "imports_from", "confidence": "EXTRACTED", "source_file": "/home/sasi/Desktop/dev/RM Orbit/Card/src/pages/CardEditor.tsx", "source_location": "L8", "weight": 1.0}, {"source": "home_sasi_desktop_dev_rm_orbit_card_src_pages_cardeditor_tsx", "target": "home_sasi_desktop_dev_rm_orbit_card_src_components_cardpreview", "relation": "imports_from", "confidence": "EXTRACTED", "source_file": "/home/sasi/Desktop/dev/RM Orbit/Card/src/pages/CardEditor.tsx", "source_location": "L9", "weight": 1.0}, {"source": "home_sasi_desktop_dev_rm_orbit_card_src_pages_cardeditor_tsx", "target": "home_sasi_desktop_dev_rm_orbit_card_src_components_personaeditor", "relation": "imports_from", "confidence": "EXTRACTED", "source_file": "/home/sasi/Desktop/dev/RM Orbit/Card/src/pages/CardEditor.tsx", "source_location": "L10", "weight": 1.0}, {"source": "home_sasi_desktop_dev_rm_orbit_card_src_pages_cardeditor_tsx", "target": "home_sasi_desktop_dev_rm_orbit_card_src_components_avatarupload", "relation": "imports_from", "confidence": "EXTRACTED", "source_file": "/home/sasi/Desktop/dev/RM Orbit/Card/src/pages/CardEditor.tsx", "source_location": "L11", "weight": 1.0}, {"source": "home_sasi_desktop_dev_rm_orbit_card_src_pages_cardeditor_tsx", "target": "cardeditor_set", "relation": "contains", "confidence": "EXTRACTED", "source_file": "/home/sasi/Desktop/dev/RM Orbit/Card/src/pages/CardEditor.tsx", "source_location": "L135", "weight": 1.0}, {"source": "home_sasi_desktop_dev_rm_orbit_card_src_pages_cardeditor_tsx", "target": "cardeditor_addlink", "relation": "contains", "confidence": "EXTRACTED", "source_file": "/home/sasi/Desktop/dev/RM Orbit/Card/src/pages/CardEditor.tsx", "source_location": "L138", "weight": 1.0}, {"source": "home_sasi_desktop_dev_rm_orbit_card_src_pages_cardeditor_tsx", "target": "cardeditor_updatelink", "relation": "contains", "confidence": "EXTRACTED", "source_file": "/home/sasi/Desktop/dev/RM Orbit/Card/src/pages/CardEditor.tsx", "source_location": "L141", "weight": 1.0}, {"source": "home_sasi_desktop_dev_rm_orbit_card_src_pages_cardeditor_tsx", "target": "cardeditor_removelink", "relation": "contains", "confidence": "EXTRACTED", "source_file": "/home/sasi/Desktop/dev/RM Orbit/Card/src/pages/CardEditor.tsx", "source_location": "L148", "weight": 1.0}, {"source": "home_sasi_desktop_dev_rm_orbit_card_src_pages_cardeditor_tsx", "target": "cardeditor_handlesave", "relation": "contains", "confidence": "EXTRACTED", "source_file": "/home/sasi/Desktop/dev/RM Orbit/Card/src/pages/CardEditor.tsx", "source_location": "L151", "weight": 1.0}, {"source": "home_sasi_desktop_dev_rm_orbit_card_src_pages_cardeditor_tsx", "target": "cardeditor_copysecret", "relation": "contains", "confidence": "EXTRACTED", "source_file": "/home/sasi/Desktop/dev/RM Orbit/Card/src/pages/CardEditor.tsx", "source_location": "L180", "weight": 1.0}, {"source": "home_sasi_desktop_dev_rm_orbit_card_src_pages_cardeditor_tsx", "target": "cardeditor_isedit", "relation": "contains", "confidence": "EXTRACTED", "source_file": "/home/sasi/Desktop/dev/RM Orbit/Card/src/pages/CardEditor.tsx", "source_location": "L408", "weight": 1.0}], "raw_calls": [{"caller_nid": "cardeditor_set", "callee": "setForm", "source_file": "/home/sasi/Desktop/dev/RM Orbit/Card/src/pages/CardEditor.tsx", "source_location": "L136"}, {"caller_nid": "cardeditor_addlink", "callee": "setForm", "source_file": "/home/sasi/Desktop/dev/RM Orbit/Card/src/pages/CardEditor.tsx", "source_location": "L139"}, {"caller_nid": "cardeditor_updatelink", "callee": "setForm", "source_file": "/home/sasi/Desktop/dev/RM Orbit/Card/src/pages/CardEditor.tsx", "source_location": "L142"}, {"caller_nid": "cardeditor_removelink", "callee": "setForm", "source_file": "/home/sasi/Desktop/dev/RM Orbit/Card/src/pages/CardEditor.tsx", "source_location": "L149"}, {"caller_nid": "cardeditor_handlesave", "callee": "setError", "source_file": "/home/sasi/Desktop/dev/RM Orbit/Card/src/pages/CardEditor.tsx", "source_location": "L152"}, {"caller_nid": "cardeditor_handlesave", "callee": "setSaving", "source_file": "/home/sasi/Desktop/dev/RM Orbit/Card/src/pages/CardEditor.tsx", "source_location": "L153"}, {"caller_nid": "cardeditor_handlesave", "callee": "updateCard", "source_file": "/home/sasi/Desktop/dev/RM Orbit/Card/src/pages/CardEditor.tsx", "source_location": "L156"}, {"caller_nid": "cardeditor_handlesave", "callee": "navigate", "source_file": "/home/sasi/Desktop/dev/RM Orbit/Card/src/pages/CardEditor.tsx", "source_location": "L167"}, {"caller_nid": "cardeditor_handlesave", "callee": "createCard", "source_file": "/home/sasi/Desktop/dev/RM Orbit/Card/src/pages/CardEditor.tsx", "source_location": "L169"}, {"caller_nid": "cardeditor_handlesave", "callee": "saveOwnedCard", "source_file": "/home/sasi/Desktop/dev/RM Orbit/Card/src/pages/CardEditor.tsx", "source_location": "L170"}, {"caller_nid": "cardeditor_handlesave", "callee": "setNewSecretKey", "source_file": "/home/sasi/Desktop/dev/RM Orbit/Card/src/pages/CardEditor.tsx", "source_location": "L171"}, {"caller_nid": "cardeditor_handlesave", "callee": "setError", "source_file": "/home/sasi/Desktop/dev/RM Orbit/Card/src/pages/CardEditor.tsx", "source_location": "L174"}, {"caller_nid": "cardeditor_handlesave", "callee": "setSaving", "source_file": "/home/sasi/Desktop/dev/RM Orbit/Card/src/pages/CardEditor.tsx", "source_location": "L176"}, {"caller_nid": "cardeditor_copysecret", "callee": "catch", "source_file": "/home/sasi/Desktop/dev/RM Orbit/Card/src/pages/CardEditor.tsx", "source_location": "L181"}, {"caller_nid": "cardeditor_copysecret", "callee": "writeText", "source_file": "/home/sasi/Desktop/dev/RM Orbit/Card/src/pages/CardEditor.tsx", "source_location": "L181"}, {"caller_nid": "cardeditor_copysecret", "callee": "setSecretKeyCopied", "source_file": "/home/sasi/Desktop/dev/RM Orbit/Card/src/pages/CardEditor.tsx", "source_location": "L182"}, {"caller_nid": "cardeditor_copysecret", "callee": "setTimeout", "source_file": "/home/sasi/Desktop/dev/RM Orbit/Card/src/pages/CardEditor.tsx", "source_location": "L183"}]}