{"nodes": [{"id": "home_sasi_desktop_dev_rm_orbit_connect_server_database_js", "label": "database.js", "file_type": "code", "source_file": "/home/sasi/Desktop/dev/RM Orbit/Connect/server/database.js", "source_location": "L1"}, {"id": "database_getusers", "label": "getUsers()", "file_type": "code", "source_file": "/home/sasi/Desktop/dev/RM Orbit/Connect/server/database.js", "source_location": "L16"}, {"id": "database_getuserbyid", "label": "getUserById()", "file_type": "code", "source_file": "/home/sasi/Desktop/dev/RM Orbit/Connect/server/database.js", "source_location": "L23"}, {"id": "database_upsertuser", "label": "upsertUser()", "file_type": "code", "source_file": "/home/sasi/Desktop/dev/RM Orbit/Connect/server/database.js", "source_location": "L29"}, {"id": "database_updateuserstatus", "label": "updateUserStatus()", "file_type": "code", "source_file": "/home/sasi/Desktop/dev/RM Orbit/Connect/server/database.js", "source_location": "L59"}, {"id": "database_getchannels", "label": "getChannels()", "file_type": "code", "source_file": "/home/sasi/Desktop/dev/RM Orbit/Connect/server/database.js", "source_location": "L73"}, {"id": "database_getchannelbyid", "label": "getChannelById()", "file_type": "code", "source_file": "/home/sasi/Desktop/dev/RM Orbit/Connect/server/database.js", "source_location": "L90"}, {"id": "database_createchannel", "label": "createChannel()", "file_type": "code", "source_file": "/home/sasi/Desktop/dev/RM Orbit/Connect/server/database.js", "source_location": "L103"}, {"id": "database_updatechannel", "label": "updateChannel()", "file_type": "code", "source_file": "/home/sasi/Desktop/dev/RM Orbit/Connect/server/database.js", "source_location": "L133"}, {"id": "database_getmessages", "label": "getMessages()", "file_type": "code", "source_file": "/home/sasi/Desktop/dev/RM Orbit/Connect/server/database.js", "source_location": "L144"}, {"id": "database_createmessage", "label": "createMessage()", "file_type": "code", "source_file": "/home/sasi/Desktop/dev/RM Orbit/Connect/server/database.js", "source_location": "L174"}, {"id": "database_updatemessage", "label": "updateMessage()", "file_type": "code", "source_file": "/home/sasi/Desktop/dev/RM Orbit/Connect/server/database.js", "source_location": "L208"}, {"id": "database_deletemessage", "label": "deleteMessage()", "file_type": "code", "source_file": "/home/sasi/Desktop/dev/RM Orbit/Connect/server/database.js", "source_location": "L224"}, {"id": "database_getthreadmessages", "label": "getThreadMessages()", "file_type": "code", "source_file": "/home/sasi/Desktop/dev/RM Orbit/Connect/server/database.js", "source_location": "L234"}, {"id": "database_addreaction", "label": "addReaction()", "file_type": "code", "source_file": "/home/sasi/Desktop/dev/RM Orbit/Connect/server/database.js", "source_location": "L254"}, {"id": "database_removereaction", "label": "removeReaction()", "file_type": "code", "source_file": "/home/sasi/Desktop/dev/RM Orbit/Connect/server/database.js", "source_location": "L275"}, {"id": "database_searchmessages", "label": "searchMessages()", "file_type": "code", "source_file": "/home/sasi/Desktop/dev/RM Orbit/Connect/server/database.js", "source_location": "L289"}, {"id": "database_pinmessage", "label": "pinMessage()", "file_type": "code", "source_file": "/home/sasi/Desktop/dev/RM Orbit/Connect/server/database.js", "source_location": "L330"}, {"id": "database_unpinmessage", "label": "unpinMessage()", "file_type": "code", "source_file": "/home/sasi/Desktop/dev/RM Orbit/Connect/server/database.js", "source_location": "L340"}, {"id": "database_getpinnedmessages", "label": "getPinnedMessages()", "file_type": "code", "source_file": "/home/sasi/Desktop/dev/RM Orbit/Connect/server/database.js", "source_location": "L346"}, {"id": "database_createnotification", "label": "createNotification()", "file_type": "code", "source_file": "/home/sasi/Desktop/dev/RM Orbit/Connect/server/database.js", "source_location": "L369"}, {"id": "database_getnotifications", "label": "getNotifications()", "file_type": "code", "source_file": "/home/sasi/Desktop/dev/RM Orbit/Connect/server/database.js", "source_location": "L375"}, {"id": "database_marknotificationread", "label": "markNotificationRead()", "file_type": "code", "source_file": "/home/sasi/Desktop/dev/RM Orbit/Connect/server/database.js", "source_location": "L389"}, {"id": "database_markallnotificationsread", "label": "markAllNotificationsRead()", "file_type": "code", "source_file": "/home/sasi/Desktop/dev/RM Orbit/Connect/server/database.js", "source_location": "L399"}, {"id": "database_disconnect", "label": "disconnect()", "file_type": "code", "source_file": "/home/sasi/Desktop/dev/RM Orbit/Connect/server/database.js", "source_location": "L416"}], "edges": [{"source": "home_sasi_desktop_dev_rm_orbit_connect_server_database_js", "target": "database_getusers", "relation": "contains", "confidence": "EXTRACTED", "source_file": "/home/sasi/Desktop/dev/RM Orbit/Connect/server/database.js", "source_location": "L16", "weight": 1.0}, {"source": "home_sasi_desktop_dev_rm_orbit_connect_server_database_js", "target": "database_getuserbyid", "relation": "contains", "confidence": "EXTRACTED", "source_file": "/home/sasi/Desktop/dev/RM Orbit/Connect/server/database.js", "source_location": "L23", "weight": 1.0}, {"source": "home_sasi_desktop_dev_rm_orbit_connect_server_database_js", "target": "database_upsertuser", "relation": "contains", "confidence": "EXTRACTED", "source_file": "/home/sasi/Desktop/dev/RM Orbit/Connect/server/database.js", "source_location": "L29", "weight": 1.0}, {"source": "home_sasi_desktop_dev_rm_orbit_connect_server_database_js", "target": "database_updateuserstatus", "relation": "contains", "confidence": "EXTRACTED", "source_file": "/home/sasi/Desktop/dev/RM Orbit/Connect/server/database.js", "source_location": "L59", "weight": 1.0}, {"source": "home_sasi_desktop_dev_rm_orbit_connect_server_database_js", "target": "database_getchannels", "relation": "contains", "confidence": "EXTRACTED", "source_file": "/home/sasi/Desktop/dev/RM Orbit/Connect/server/database.js", "source_location": "L73", "weight": 1.0}, {"source": "home_sasi_desktop_dev_rm_orbit_connect_server_database_js", "target": "database_getchannelbyid", "relation": "contains", "confidence": "EXTRACTED", "source_file": "/home/sasi/Desktop/dev/RM Orbit/Connect/server/database.js", "source_location": "L90", "weight": 1.0}, {"source": "home_sasi_desktop_dev_rm_orbit_connect_server_database_js", "target": "database_createchannel", "relation": "contains", "confidence": "EXTRACTED", "source_file": "/home/sasi/Desktop/dev/RM Orbit/Connect/server/database.js", "source_location": "L103", "weight": 1.0}, {"source": "home_sasi_desktop_dev_rm_orbit_connect_server_database_js", "target": "database_updatechannel", "relation": "contains", "confidence": "EXTRACTED", "source_file": "/home/sasi/Desktop/dev/RM Orbit/Connect/server/database.js", "source_location": "L133", "weight": 1.0}, {"source": "home_sasi_desktop_dev_rm_orbit_connect_server_database_js", "target": "database_getmessages", "relation": "contains", "confidence": "EXTRACTED", "source_file": "/home/sasi/Desktop/dev/RM Orbit/Connect/server/database.js", "source_location": "L144", "weight": 1.0}, {"source": "home_sasi_desktop_dev_rm_orbit_connect_server_database_js", "target": "database_createmessage", "relation": "contains", "confidence": "EXTRACTED", "source_file": "/home/sasi/Desktop/dev/RM Orbit/Connect/server/database.js", "source_location": "L174", "weight": 1.0}, {"source": "home_sasi_desktop_dev_rm_orbit_connect_server_database_js", "target": "database_updatemessage", "relation": "contains", "confidence": "EXTRACTED", "source_file": "/home/sasi/Desktop/dev/RM Orbit/Connect/server/database.js", "source_location": "L208", "weight": 1.0}, {"source": "home_sasi_desktop_dev_rm_orbit_connect_server_database_js", "target": "database_deletemessage", "relation": "contains", "confidence": "EXTRACTED", "source_file": "/home/sasi/Desktop/dev/RM Orbit/Connect/server/database.js", "source_location": "L224", "weight": 1.0}, {"source": "home_sasi_desktop_dev_rm_orbit_connect_server_database_js", "target": "database_getthreadmessages", "relation": "contains", "confidence": "EXTRACTED", "source_file": "/home/sasi/Desktop/dev/RM Orbit/Connect/server/database.js", "source_location": "L234", "weight": 1.0}, {"source": "home_sasi_desktop_dev_rm_orbit_connect_server_database_js", "target": "database_addreaction", "relation": "contains", "confidence": "EXTRACTED", "source_file": "/home/sasi/Desktop/dev/RM Orbit/Connect/server/database.js", "source_location": "L254", "weight": 1.0}, {"source": "home_sasi_desktop_dev_rm_orbit_connect_server_database_js", "target": "database_removereaction", "relation": "contains", "confidence": "EXTRACTED", "source_file": "/home/sasi/Desktop/dev/RM Orbit/Connect/server/database.js", "source_location": "L275", "weight": 1.0}, {"source": "home_sasi_desktop_dev_rm_orbit_connect_server_database_js", "target": "database_searchmessages", "relation": "contains", "confidence": "EXTRACTED", "source_file": "/home/sasi/Desktop/dev/RM Orbit/Connect/server/database.js", "source_location": "L289", "weight": 1.0}, {"source": "home_sasi_desktop_dev_rm_orbit_connect_server_database_js", "target": "database_pinmessage", "relation": "contains", "confidence": "EXTRACTED", "source_file": "/home/sasi/Desktop/dev/RM Orbit/Connect/server/database.js", "source_location": "L330", "weight": 1.0}, {"source": "home_sasi_desktop_dev_rm_orbit_connect_server_database_js", "target": "database_unpinmessage", "relation": "contains", "confidence": "EXTRACTED", "source_file": "/home/sasi/Desktop/dev/RM Orbit/Connect/server/database.js", "source_location": "L340", "weight": 1.0}, {"source": "home_sasi_desktop_dev_rm_orbit_connect_server_database_js", "target": "database_getpinnedmessages", "relation": "contains", "confidence": "EXTRACTED", "source_file": "/home/sasi/Desktop/dev/RM Orbit/Connect/server/database.js", "source_location": "L346", "weight": 1.0}, {"source": "home_sasi_desktop_dev_rm_orbit_connect_server_database_js", "target": "database_createnotification", "relation": "contains", "confidence": "EXTRACTED", "source_file": "/home/sasi/Desktop/dev/RM Orbit/Connect/server/database.js", "source_location": "L369", "weight": 1.0}, {"source": "home_sasi_desktop_dev_rm_orbit_connect_server_database_js", "target": "database_getnotifications", "relation": "contains", "confidence": "EXTRACTED", "source_file": "/home/sasi/Desktop/dev/RM Orbit/Connect/server/database.js", "source_location": "L375", "weight": 1.0}, {"source": "home_sasi_desktop_dev_rm_orbit_connect_server_database_js", "target": "database_marknotificationread", "relation": "contains", "confidence": "EXTRACTED", "source_file": "/home/sasi/Desktop/dev/RM Orbit/Connect/server/database.js", "source_location": "L389", "weight": 1.0}, {"source": "home_sasi_desktop_dev_rm_orbit_connect_server_database_js", "target": "database_markallnotificationsread", "relation": "contains", "confidence": "EXTRACTED", "source_file": "/home/sasi/Desktop/dev/RM Orbit/Connect/server/database.js", "source_location": "L399", "weight": 1.0}, {"source": "home_sasi_desktop_dev_rm_orbit_connect_server_database_js", "target": "database_disconnect", "relation": "contains", "confidence": "EXTRACTED", "source_file": "/home/sasi/Desktop/dev/RM Orbit/Connect/server/database.js", "source_location": "L416", "weight": 1.0}], "raw_calls": [{"caller_nid": "database_getusers", "callee": "findMany", "source_file": "/home/sasi/Desktop/dev/RM Orbit/Connect/server/database.js", "source_location": "L17"}, {"caller_nid": "database_getuserbyid", "callee": "findFirst", "source_file": "/home/sasi/Desktop/dev/RM Orbit/Connect/server/database.js", "source_location": "L24"}, {"caller_nid": "database_upsertuser", "callee": "upsert", "source_file": "/home/sasi/Desktop/dev/RM Orbit/Connect/server/database.js", "source_location": "L32"}, {"caller_nid": "database_updateuserstatus", "callee": "update", "source_file": "/home/sasi/Desktop/dev/RM Orbit/Connect/server/database.js", "source_location": "L60"}, {"caller_nid": "database_getchannels", "callee": "findMany", "source_file": "/home/sasi/Desktop/dev/RM Orbit/Connect/server/database.js", "source_location": "L74"}, {"caller_nid": "database_getchannelbyid", "callee": "findFirst", "source_file": "/home/sasi/Desktop/dev/RM Orbit/Connect/server/database.js", "source_location": "L91"}, {"caller_nid": "database_createchannel", "callee": "create", "source_file": "/home/sasi/Desktop/dev/RM Orbit/Connect/server/database.js", "source_location": "L106"}, {"caller_nid": "database_createchannel", "callee": "map", "source_file": "/home/sasi/Desktop/dev/RM Orbit/Connect/server/database.js", "source_location": "L117"}, {"caller_nid": "database_updatechannel", "callee": "update", "source_file": "/home/sasi/Desktop/dev/RM Orbit/Connect/server/database.js", "source_location": "L134"}, {"caller_nid": "database_getmessages", "callee": "findMany", "source_file": "/home/sasi/Desktop/dev/RM Orbit/Connect/server/database.js", "source_location": "L155"}, {"caller_nid": "database_createmessage", "callee": "create", "source_file": "/home/sasi/Desktop/dev/RM Orbit/Connect/server/database.js", "source_location": "L185"}, {"caller_nid": "database_createmessage", "callee": "map", "source_file": "/home/sasi/Desktop/dev/RM Orbit/Connect/server/database.js", "source_location": "L196"}, {"caller_nid": "database_updatemessage", "callee": "update", "source_file": "/home/sasi/Desktop/dev/RM Orbit/Connect/server/database.js", "source_location": "L209"}, {"caller_nid": "database_deletemessage", "callee": "update", "source_file": "/home/sasi/Desktop/dev/RM Orbit/Connect/server/database.js", "source_location": "L225"}, {"caller_nid": "database_getthreadmessages", "callee": "findMany", "source_file": "/home/sasi/Desktop/dev/RM Orbit/Connect/server/database.js", "source_location": "L235"}, {"caller_nid": "database_addreaction", "callee": "upsert", "source_file": "/home/sasi/Desktop/dev/RM Orbit/Connect/server/database.js", "source_location": "L255"}, {"caller_nid": "database_removereaction", "callee": "deleteMany", "source_file": "/home/sasi/Desktop/dev/RM Orbit/Connect/server/database.js", "source_location": "L276"}, {"caller_nid": "database_searchmessages", "callee": "findMany", "source_file": "/home/sasi/Desktop/dev/RM Orbit/Connect/server/database.js", "source_location": "L315"}, {"caller_nid": "database_pinmessage", "callee": "create", "source_file": "/home/sasi/Desktop/dev/RM Orbit/Connect/server/database.js", "source_location": "L331"}, {"caller_nid": "database_unpinmessage", "callee": "delete", "source_file": "/home/sasi/Desktop/dev/RM Orbit/Connect/server/database.js", "source_location": "L341"}, {"caller_nid": "database_getpinnedmessages", "callee": "findMany", "source_file": "/home/sasi/Desktop/dev/RM Orbit/Connect/server/database.js", "source_location": "L347"}, {"caller_nid": "database_createnotification", "callee": "create", "source_file": "/home/sasi/Desktop/dev/RM Orbit/Connect/server/database.js", "source_location": "L370"}, {"caller_nid": "database_getnotifications", "callee": "findMany", "source_file": "/home/sasi/Desktop/dev/RM Orbit/Connect/server/database.js", "source_location": "L382"}, {"caller_nid": "database_marknotificationread", "callee": "update", "source_file": "/home/sasi/Desktop/dev/RM Orbit/Connect/server/database.js", "source_location": "L390"}, {"caller_nid": "database_markallnotificationsread", "callee": "updateMany", "source_file": "/home/sasi/Desktop/dev/RM Orbit/Connect/server/database.js", "source_location": "L400"}, {"caller_nid": "database_disconnect", "callee": "$disconnect", "source_file": "/home/sasi/Desktop/dev/RM Orbit/Connect/server/database.js", "source_location": "L417"}]}