{"nodes": [{"id": "home_sasi_desktop_dev_rm_orbit_capital_hub_backend_app_main_py", "label": "main.py", "file_type": "code", "source_file": "/home/sasi/Desktop/dev/RM Orbit/Capital Hub/backend/app/main.py", "source_location": "L1"}, {"id": "main_health_check", "label": "health_check()", "file_type": "code", "source_file": "/home/sasi/Desktop/dev/RM Orbit/Capital Hub/backend/app/main.py", "source_location": "L16"}, {"id": "main_serve_spa", "label": "serve_spa()", "file_type": "code", "source_file": "/home/sasi/Desktop/dev/RM Orbit/Capital Hub/backend/app/main.py", "source_location": "L34"}], "edges": [{"source": "home_sasi_desktop_dev_rm_orbit_capital_hub_backend_app_main_py", "target": "fastapi", "relation": "imports_from", "confidence": "EXTRACTED", "source_file": "/home/sasi/Desktop/dev/RM Orbit/Capital Hub/backend/app/main.py", "source_location": "L1", "weight": 1.0}, {"source": "home_sasi_desktop_dev_rm_orbit_capital_hub_backend_app_main_py", "target": "fastapi_middleware_cors", "relation": "imports_from", "confidence": "EXTRACTED", "source_file": "/home/sasi/Desktop/dev/RM Orbit/Capital Hub/backend/app/main.py", "source_location": "L2", "weight": 1.0}, {"source": "home_sasi_desktop_dev_rm_orbit_capital_hub_backend_app_main_py", "target": "app_routes", "relation": "imports_from", "confidence": "EXTRACTED", "source_file": "/home/sasi/Desktop/dev/RM Orbit/Capital Hub/backend/app/main.py", "source_location": "L3", "weight": 1.0}, {"source": "home_sasi_desktop_dev_rm_orbit_capital_hub_backend_app_main_py", "target": "main_health_check", "relation": "contains", "confidence": "EXTRACTED", "source_file": "/home/sasi/Desktop/dev/RM Orbit/Capital Hub/backend/app/main.py", "source_location": "L16", "weight": 1.0}, {"source": "home_sasi_desktop_dev_rm_orbit_capital_hub_backend_app_main_py", "target": "fastapi_staticfiles", "relation": "imports_from", "confidence": "EXTRACTED", "source_file": "/home/sasi/Desktop/dev/RM Orbit/Capital Hub/backend/app/main.py", "source_location": "L20", "weight": 1.0}, {"source": "home_sasi_desktop_dev_rm_orbit_capital_hub_backend_app_main_py", "target": "fastapi_responses", "relation": "imports_from", "confidence": "EXTRACTED", "source_file": "/home/sasi/Desktop/dev/RM Orbit/Capital Hub/backend/app/main.py", "source_location": "L21", "weight": 1.0}, {"source": "home_sasi_desktop_dev_rm_orbit_capital_hub_backend_app_main_py", "target": "pathlib", "relation": "imports_from", "confidence": "EXTRACTED", "source_file": "/home/sasi/Desktop/dev/RM Orbit/Capital Hub/backend/app/main.py", "source_location": "L22", "weight": 1.0}, {"source": "home_sasi_desktop_dev_rm_orbit_capital_hub_backend_app_main_py", "target": "fastapi", "relation": "imports_from", "confidence": "EXTRACTED", "source_file": "/home/sasi/Desktop/dev/RM Orbit/Capital Hub/backend/app/main.py", "source_location": "L23", "weight": 1.0}, {"source": "home_sasi_desktop_dev_rm_orbit_capital_hub_backend_app_main_py", "target": "main_serve_spa", "relation": "contains", "confidence": "EXTRACTED", "source_file": "/home/sasi/Desktop/dev/RM Orbit/Capital Hub/backend/app/main.py", "source_location": "L34", "weight": 1.0}], "raw_calls": [{"caller_nid": "main_serve_spa", "callee": "startswith", "source_file": "/home/sasi/Desktop/dev/RM Orbit/Capital Hub/backend/app/main.py", "source_location": "L36"}, {"caller_nid": "main_serve_spa", "callee": "startswith", "source_file": "/home/sasi/Desktop/dev/RM Orbit/Capital Hub/backend/app/main.py", "source_location": "L36"}, {"caller_nid": "main_serve_spa", "callee": "is_file", "source_file": "/home/sasi/Desktop/dev/RM Orbit/Capital Hub/backend/app/main.py", "source_location": "L40"}, {"caller_nid": "main_serve_spa", "callee": "FileResponse", "source_file": "/home/sasi/Desktop/dev/RM Orbit/Capital Hub/backend/app/main.py", "source_location": "L41"}, {"caller_nid": "main_serve_spa", "callee": "FileResponse", "source_file": "/home/sasi/Desktop/dev/RM Orbit/Capital Hub/backend/app/main.py", "source_location": "L43"}]}