{"nodes": [{"id": "home_sasi_desktop_dev_rm_orbit_snitch_backend_secure_service_test_js", "label": "secure-service.test.js", "file_type": "code", "source_file": "/home/sasi/Desktop/dev/RM Orbit/Snitch/backend/secure-service.test.js", "source_location": "L1"}, {"id": "secure_service_test_signtoken", "label": "signToken()", "file_type": "code", "source_file": "/home/sasi/Desktop/dev/RM Orbit/Snitch/backend/secure-service.test.js", "source_location": "L217"}, {"id": "secure_service_test_adddays", "label": "addDays()", "file_type": "code", "source_file": "/home/sasi/Desktop/dev/RM Orbit/Snitch/backend/secure-service.test.js", "source_location": "L233"}, {"id": "secure_service_test_withserver", "label": "withServer()", "file_type": "code", "source_file": "/home/sasi/Desktop/dev/RM Orbit/Snitch/backend/secure-service.test.js", "source_location": "L239"}, {"id": "secure_service_test_request", "label": "request()", "file_type": "code", "source_file": "/home/sasi/Desktop/dev/RM Orbit/Snitch/backend/secure-service.test.js", "source_location": "L264"}], "edges": [{"source": "home_sasi_desktop_dev_rm_orbit_snitch_backend_secure_service_test_js", "target": "secure_service_test_signtoken", "relation": "contains", "confidence": "EXTRACTED", "source_file": "/home/sasi/Desktop/dev/RM Orbit/Snitch/backend/secure-service.test.js", "source_location": "L217", "weight": 1.0}, {"source": "home_sasi_desktop_dev_rm_orbit_snitch_backend_secure_service_test_js", "target": "secure_service_test_adddays", "relation": "contains", "confidence": "EXTRACTED", "source_file": "/home/sasi/Desktop/dev/RM Orbit/Snitch/backend/secure-service.test.js", "source_location": "L233", "weight": 1.0}, {"source": "home_sasi_desktop_dev_rm_orbit_snitch_backend_secure_service_test_js", "target": "secure_service_test_withserver", "relation": "contains", "confidence": "EXTRACTED", "source_file": "/home/sasi/Desktop/dev/RM Orbit/Snitch/backend/secure-service.test.js", "source_location": "L239", "weight": 1.0}, {"source": "home_sasi_desktop_dev_rm_orbit_snitch_backend_secure_service_test_js", "target": "secure_service_test_request", "relation": "contains", "confidence": "EXTRACTED", "source_file": "/home/sasi/Desktop/dev/RM Orbit/Snitch/backend/secure-service.test.js", "source_location": "L264", "weight": 1.0}], "raw_calls": [{"caller_nid": "secure_service_test_signtoken", "callee": "sign", "source_file": "/home/sasi/Desktop/dev/RM Orbit/Snitch/backend/secure-service.test.js", "source_location": "L218"}, {"caller_nid": "secure_service_test_adddays", "callee": "valueOf", "source_file": "/home/sasi/Desktop/dev/RM Orbit/Snitch/backend/secure-service.test.js", "source_location": "L234"}, {"caller_nid": "secure_service_test_adddays", "callee": "setUTCDate", "source_file": "/home/sasi/Desktop/dev/RM Orbit/Snitch/backend/secure-service.test.js", "source_location": "L235"}, {"caller_nid": "secure_service_test_adddays", "callee": "getUTCDate", "source_file": "/home/sasi/Desktop/dev/RM Orbit/Snitch/backend/secure-service.test.js", "source_location": "L235"}, {"caller_nid": "secure_service_test_withserver", "callee": "createSecureApp", "source_file": "/home/sasi/Desktop/dev/RM Orbit/Snitch/backend/secure-service.test.js", "source_location": "L240"}, {"caller_nid": "secure_service_test_withserver", "callee": "createSecureStore", "source_file": "/home/sasi/Desktop/dev/RM Orbit/Snitch/backend/secure-service.test.js", "source_location": "L241"}, {"caller_nid": "secure_service_test_withserver", "callee": "createNoopEventPublisher", "source_file": "/home/sasi/Desktop/dev/RM Orbit/Snitch/backend/secure-service.test.js", "source_location": "L242"}, {"caller_nid": "secure_service_test_withserver", "callee": "createServer", "source_file": "/home/sasi/Desktop/dev/RM Orbit/Snitch/backend/secure-service.test.js", "source_location": "L245"}, {"caller_nid": "secure_service_test_withserver", "callee": "address", "source_file": "/home/sasi/Desktop/dev/RM Orbit/Snitch/backend/secure-service.test.js", "source_location": "L247"}, {"caller_nid": "secure_service_test_withserver", "callee": "run", "source_file": "/home/sasi/Desktop/dev/RM Orbit/Snitch/backend/secure-service.test.js", "source_location": "L250"}, {"caller_nid": "secure_service_test_request", "callee": "fetch", "source_file": "/home/sasi/Desktop/dev/RM Orbit/Snitch/backend/secure-service.test.js", "source_location": "L274"}, {"caller_nid": "secure_service_test_request", "callee": "stringify", "source_file": "/home/sasi/Desktop/dev/RM Orbit/Snitch/backend/secure-service.test.js", "source_location": "L277"}, {"caller_nid": "secure_service_test_request", "callee": "json", "source_file": "/home/sasi/Desktop/dev/RM Orbit/Snitch/backend/secure-service.test.js", "source_location": "L282"}]}