{"nodes": [{"id": "home_sasi_desktop_dev_rm_orbit_rmmeet_src_pages_roompage_jsx", "label": "RoomPage.jsx", "file_type": "code", "source_file": "/home/sasi/Desktop/dev/RM Orbit/RMMeet/src/pages/RoomPage.jsx", "source_location": "L1"}, {"id": "roompage_spinner", "label": "Spinner()", "file_type": "code", "source_file": "/home/sasi/Desktop/dev/RM Orbit/RMMeet/src/pages/RoomPage.jsx", "source_location": "L23"}, {"id": "roompage_fatalerror", "label": "FatalError()", "file_type": "code", "source_file": "/home/sasi/Desktop/dev/RM Orbit/RMMeet/src/pages/RoomPage.jsx", "source_location": "L34"}, {"id": "roompage_videogrid", "label": "VideoGrid()", "file_type": "code", "source_file": "/home/sasi/Desktop/dev/RM Orbit/RMMeet/src/pages/RoomPage.jsx", "source_location": "L73"}, {"id": "roompage_roomheader", "label": "RoomHeader()", "file_type": "code", "source_file": "/home/sasi/Desktop/dev/RM Orbit/RMMeet/src/pages/RoomPage.jsx", "source_location": "L117"}, {"id": "roompage_localvideopip", "label": "LocalVideoPip()", "file_type": "code", "source_file": "/home/sasi/Desktop/dev/RM Orbit/RMMeet/src/pages/RoomPage.jsx", "source_location": "L190"}, {"id": "roompage_roompage", "label": "RoomPage()", "file_type": "code", "source_file": "/home/sasi/Desktop/dev/RM Orbit/RMMeet/src/pages/RoomPage.jsx", "source_location": "L235"}], "edges": [{"source": "home_sasi_desktop_dev_rm_orbit_rmmeet_src_pages_roompage_jsx", "target": "react", "relation": "imports_from", "confidence": "EXTRACTED", "source_file": "/home/sasi/Desktop/dev/RM Orbit/RMMeet/src/pages/RoomPage.jsx", "source_location": "L14", "weight": 1.0}, {"source": "home_sasi_desktop_dev_rm_orbit_rmmeet_src_pages_roompage_jsx", "target": "react_router_dom", "relation": "imports_from", "confidence": "EXTRACTED", "source_file": "/home/sasi/Desktop/dev/RM Orbit/RMMeet/src/pages/RoomPage.jsx", "source_location": "L15", "weight": 1.0}, {"source": "home_sasi_desktop_dev_rm_orbit_rmmeet_src_pages_roompage_jsx", "target": "home_sasi_desktop_dev_rm_orbit_rmmeet_src_api_ts", "relation": "imports_from", "confidence": "EXTRACTED", "source_file": "/home/sasi/Desktop/dev/RM Orbit/RMMeet/src/pages/RoomPage.jsx", "source_location": "L16", "weight": 1.0}, {"source": "home_sasi_desktop_dev_rm_orbit_rmmeet_src_pages_roompage_jsx", "target": "home_sasi_desktop_dev_rm_orbit_rmmeet_src_hooks_usewebrtc_ts", "relation": "imports_from", "confidence": "EXTRACTED", "source_file": "/home/sasi/Desktop/dev/RM Orbit/RMMeet/src/pages/RoomPage.jsx", "source_location": "L17", "weight": 1.0}, {"source": "home_sasi_desktop_dev_rm_orbit_rmmeet_src_pages_roompage_jsx", "target": "home_sasi_desktop_dev_rm_orbit_rmmeet_src_components_videotile_tsx", "relation": "imports_from", "confidence": "EXTRACTED", "source_file": "/home/sasi/Desktop/dev/RM Orbit/RMMeet/src/pages/RoomPage.jsx", "source_location": "L18", "weight": 1.0}, {"source": "home_sasi_desktop_dev_rm_orbit_rmmeet_src_pages_roompage_jsx", "target": "home_sasi_desktop_dev_rm_orbit_rmmeet_src_components_toolbar_tsx", "relation": "imports_from", "confidence": "EXTRACTED", "source_file": "/home/sasi/Desktop/dev/RM Orbit/RMMeet/src/pages/RoomPage.jsx", "source_location": "L19", "weight": 1.0}, {"source": "home_sasi_desktop_dev_rm_orbit_rmmeet_src_pages_roompage_jsx", "target": "roompage_spinner", "relation": "contains", "confidence": "EXTRACTED", "source_file": "/home/sasi/Desktop/dev/RM Orbit/RMMeet/src/pages/RoomPage.jsx", "source_location": "L23", "weight": 1.0}, {"source": "home_sasi_desktop_dev_rm_orbit_rmmeet_src_pages_roompage_jsx", "target": "roompage_fatalerror", "relation": "contains", "confidence": "EXTRACTED", "source_file": "/home/sasi/Desktop/dev/RM Orbit/RMMeet/src/pages/RoomPage.jsx", "source_location": "L34", "weight": 1.0}, {"source": "home_sasi_desktop_dev_rm_orbit_rmmeet_src_pages_roompage_jsx", "target": "roompage_videogrid", "relation": "contains", "confidence": "EXTRACTED", "source_file": "/home/sasi/Desktop/dev/RM Orbit/RMMeet/src/pages/RoomPage.jsx", "source_location": "L73", "weight": 1.0}, {"source": "home_sasi_desktop_dev_rm_orbit_rmmeet_src_pages_roompage_jsx", "target": "roompage_roomheader", "relation": "contains", "confidence": "EXTRACTED", "source_file": "/home/sasi/Desktop/dev/RM Orbit/RMMeet/src/pages/RoomPage.jsx", "source_location": "L117", "weight": 1.0}, {"source": "home_sasi_desktop_dev_rm_orbit_rmmeet_src_pages_roompage_jsx", "target": "roompage_localvideopip", "relation": "contains", "confidence": "EXTRACTED", "source_file": "/home/sasi/Desktop/dev/RM Orbit/RMMeet/src/pages/RoomPage.jsx", "source_location": "L190", "weight": 1.0}, {"source": "home_sasi_desktop_dev_rm_orbit_rmmeet_src_pages_roompage_jsx", "target": "roompage_roompage", "relation": "contains", "confidence": "EXTRACTED", "source_file": "/home/sasi/Desktop/dev/RM Orbit/RMMeet/src/pages/RoomPage.jsx", "source_location": "L235", "weight": 1.0}], "raw_calls": [{"caller_nid": "roompage_videogrid", "callee": "from", "source_file": "/home/sasi/Desktop/dev/RM Orbit/RMMeet/src/pages/RoomPage.jsx", "source_location": "L74"}, {"caller_nid": "roompage_videogrid", "callee": "entries", "source_file": "/home/sasi/Desktop/dev/RM Orbit/RMMeet/src/pages/RoomPage.jsx", "source_location": "L74"}, {"caller_nid": "roompage_videogrid", "callee": "toString", "source_file": "/home/sasi/Desktop/dev/RM Orbit/RMMeet/src/pages/RoomPage.jsx", "source_location": "L98"}, {"caller_nid": "roompage_videogrid", "callee": "min", "source_file": "/home/sasi/Desktop/dev/RM Orbit/RMMeet/src/pages/RoomPage.jsx", "source_location": "L98"}, {"caller_nid": "roompage_videogrid", "callee": "map", "source_file": "/home/sasi/Desktop/dev/RM Orbit/RMMeet/src/pages/RoomPage.jsx", "source_location": "L99"}, {"caller_nid": "roompage_videogrid", "callee": "slice", "source_file": "/home/sasi/Desktop/dev/RM Orbit/RMMeet/src/pages/RoomPage.jsx", "source_location": "L99"}, {"caller_nid": "roompage_roomheader", "callee": "useState", "source_file": "/home/sasi/Desktop/dev/RM Orbit/RMMeet/src/pages/RoomPage.jsx", "source_location": "L118"}, {"caller_nid": "roompage_localvideopip", "callee": "useRef", "source_file": "/home/sasi/Desktop/dev/RM Orbit/RMMeet/src/pages/RoomPage.jsx", "source_location": "L191"}, {"caller_nid": "roompage_localvideopip", "callee": "useEffect", "source_file": "/home/sasi/Desktop/dev/RM Orbit/RMMeet/src/pages/RoomPage.jsx", "source_location": "L193"}, {"caller_nid": "roompage_localvideopip", "callee": "toUpperCase", "source_file": "/home/sasi/Desktop/dev/RM Orbit/RMMeet/src/pages/RoomPage.jsx", "source_location": "L222"}, {"caller_nid": "roompage_roompage", "callee": "useParams", "source_file": "/home/sasi/Desktop/dev/RM Orbit/RMMeet/src/pages/RoomPage.jsx", "source_location": "L236"}, {"caller_nid": "roompage_roompage", "callee": "useNavigate", "source_file": "/home/sasi/Desktop/dev/RM Orbit/RMMeet/src/pages/RoomPage.jsx", "source_location": "L237"}, {"caller_nid": "roompage_roompage", "callee": "useLocation", "source_file": "/home/sasi/Desktop/dev/RM Orbit/RMMeet/src/pages/RoomPage.jsx", "source_location": "L238"}, {"caller_nid": "roompage_roompage", "callee": "useEffect", "source_file": "/home/sasi/Desktop/dev/RM Orbit/RMMeet/src/pages/RoomPage.jsx", "source_location": "L243"}, {"caller_nid": "roompage_roompage", "callee": "useState", "source_file": "/home/sasi/Desktop/dev/RM Orbit/RMMeet/src/pages/RoomPage.jsx", "source_location": "L249"}, {"caller_nid": "roompage_roompage", "callee": "useState", "source_file": "/home/sasi/Desktop/dev/RM Orbit/RMMeet/src/pages/RoomPage.jsx", "source_location": "L250"}, {"caller_nid": "roompage_roompage", "callee": "useState", "source_file": "/home/sasi/Desktop/dev/RM Orbit/RMMeet/src/pages/RoomPage.jsx", "source_location": "L251"}, {"caller_nid": "roompage_roompage", "callee": "useState", "source_file": "/home/sasi/Desktop/dev/RM Orbit/RMMeet/src/pages/RoomPage.jsx", "source_location": "L252"}, {"caller_nid": "roompage_roompage", "callee": "useState", "source_file": "/home/sasi/Desktop/dev/RM Orbit/RMMeet/src/pages/RoomPage.jsx", "source_location": "L253"}, {"caller_nid": "roompage_roompage", "callee": "useEffect", "source_file": "/home/sasi/Desktop/dev/RM Orbit/RMMeet/src/pages/RoomPage.jsx", "source_location": "L256"}, {"caller_nid": "roompage_roompage", "callee": "useWebRTC", "source_file": "/home/sasi/Desktop/dev/RM Orbit/RMMeet/src/pages/RoomPage.jsx", "source_location": "L291"}, {"caller_nid": "roompage_roompage", "callee": "useCallback", "source_file": "/home/sasi/Desktop/dev/RM Orbit/RMMeet/src/pages/RoomPage.jsx", "source_location": "L297"}]}